setup.py
bitbucket/__init__.py
bitbucket/cli.py
bitbucket/config.py
bitbucket/repositories.py
bitbucket/scm.py
bitbucket_cli.egg-info/PKG-INFO
bitbucket_cli.egg-info/SOURCES.txt
bitbucket_cli.egg-info/dependency_links.txt
bitbucket_cli.egg-info/entry_points.txt
bitbucket_cli.egg-info/requires.txt
bitbucket_cli.egg-info/top_level.txt