Metadata-Version: 1.0
Name: bitbucket-cli
Version: 0.1.1
Summary: BitBucket command line interface
Home-page: UNKNOWN
Author: Zhehao Mao
Author-email: zhehao.mao@gmail.com
License: UNKNOWN
Platform: UNKNOWN
